odoo/addons/delivery_price_method/README.rst
odoo/addons/delivery_price_method/__init__.py
odoo/addons/delivery_price_method/__manifest__.py
odoo/addons/delivery_price_method/i18n/delivery_price_method.pot
odoo/addons/delivery_price_method/i18n/es.po
odoo/addons/delivery_price_method/i18n/es_CL.po
odoo/addons/delivery_price_method/i18n/es_VE.po
odoo/addons/delivery_price_method/i18n/fr.po
odoo/addons/delivery_price_method/i18n/it.po
odoo/addons/delivery_price_method/i18n/pt.po
odoo/addons/delivery_price_method/models/__init__.py
odoo/addons/delivery_price_method/models/delivery_carrier.py
odoo/addons/delivery_price_method/readme/CONTRIBUTORS.md
odoo/addons/delivery_price_method/readme/DESCRIPTION.md
odoo/addons/delivery_price_method/readme/USAGE.md
odoo/addons/delivery_price_method/static/description/icon.png
odoo/addons/delivery_price_method/static/description/index.html
odoo/addons/delivery_price_method/tests/__init__.py
odoo/addons/delivery_price_method/tests/common.py
odoo/addons/delivery_price_method/tests/test_delivery_price_method.py
odoo/addons/delivery_price_method/views/delivery_carrier_views.xml
odoo_addon_delivery_price_method-18.0.1.0.0.2.dist-info/METADATA
odoo_addon_delivery_price_method-18.0.1.0.0.2.dist-info/WHEEL
odoo_addon_delivery_price_method-18.0.1.0.0.2.dist-info/top_level.txt
odoo_addon_delivery_price_method-18.0.1.0.0.2.dist-info/RECORD
