Metadata-Version: 2.1
Name: odoo-addon-delivery_price_method
Version: 18.0.1.0.0.2
Requires-Python: >=3.10
Requires-Dist: odoo==18.0.*
Summary: Force a fixed or rule price calculation on Delivery Methods, for example to override a webservice provided prices.
Home-page: https://github.com/OCA/delivery-carrier
License: AGPL-3
Author: Trey (www.trey.es), Odoo Community Association (OCA)
Author-email: support@odoo-community.org
Classifier: Programming Language :: Python
Classifier: Framework :: Odoo
Classifier: Framework :: Odoo :: 18.0
Classifier: License :: OSI Approved :: GNU Affero General Public License v3
Classifier: Development Status :: 5 - Production/Stable
